{
  "ai": {
    "activity": "DIURNAL",
    "attacking": "BASIC",
    "climbing": "NONE",
    "following": "NORMAL",
    "jumping": "BASIC",
    "response": "CALM",
    "stalking": "NONE",
    "taming": "NONE",
    "untaming": "NONE",
    "moving": "FLIGHT",
    "waterAbility": "ATTACK"
  },
  "stats": {
    "damageBase": 12,
    "damageMax": 12,
    "healthBase": 12,
    "healthMax": 64,
    "speedBase": 0.2,
    "speedMax": 0.35,
    "armorBase": 5,
    "armorMax": 15,
    "knockBackResistanceBase": 0.5,
    "knockBackResistanceMax": 1
  },
  "adultAgeDays": 6,
  "breaksBlocks": true,
  "canBeRidden": false,
  "diet": "CARNIVORE",
  "maxHunger": 175,
  "maxPopulation": 7,
  "scaleBase": 0.4,
  "scaleMax": 2,
  "teenAgeDays": 5
}