{
  "schemaVersion": 1,
  "id": "${modId}",
  "version": "${modVersion}",
  "name": "${modName}",
  "description": "${modDescription}",
  "authors": [
    "Flo",
    "SealManVI",
    "Dipple_Effect",
    "TotallyNotAHobo",
    "DarkPred",
    "Javaraptor",
    "DDinoDan",
    "Indominator",
    "Robberti08",
    "ASDFGirlS7",
    "Totemaster"
  ],
  "contact": {
    "sources": "https://github.com/TeamFossilsArcheology/FossilsArcheologyRevival",
    "issues": "https://github.com/TeamFossilsArcheology/FossilsArcheologyRevival/issues"
  },
  "license": "${modLicense}",
  "icon": "fossils.png",
  "environment": "*",
  "entrypoints": {
    "main": [
      "com.github.teamfossilsarcheology.fossil.fabric.FossilFabric"
    ],
    "client": [
      "com.github.teamfossilsarcheology.fossil.fabric.FossilFabricClient"
    ],
    "terrablender": [
      "com.github.teamfossilsarcheology.fossil.fabric.FossilFabric"
    ],
    "cardinal-components-entity": [
      "com.github.teamfossilsarcheology.fossil.fabric.FossilFabric"
    ],
    "rei_client": [
      "com.github.teamfossilsarcheology.fossil.compat.rei.FossilREIClientPlugin"
    ],
    "rei_common": [
      "com.github.teamfossilsarcheology.fossil.compat.rei.FossilREICommonPlugin"
    ]
  },
  "mixins": [
    "fossil_fabric.mixins.json"
  ],
  "depends": {
    "fabric": "*",
    "minecraft": ">=${minecraftVersion}",
    "architectury": ">=4.9.83",
    "geckolib3": ">=3.0.62",
    "terrablender": ">=1.2.0",
    "cardinal-components-base": ">=4.1.4",
    "multipartsupport": ">=0.23.0"
  },
  "suggests": {
    "cloth_config": ">=6.3.81",
    "roughlyenoughitems": ">=8.3.495"
  },
  "custom": {
    "cardinal-components": [
      "fossil:mammal",
      "fossil:first_hatch"
    ]
  }
}