{
	"format_version": "1.12.0",
	"minecraft:geometry": [
		{
			"description": {
				"identifier": "geometry.unknown",
				"texture_width": 205,
				"texture_height": 80,
				"visible_bounds_width": 7,
				"visible_bounds_height": 2.5,
				"visible_bounds_offset": [0, 0.75, 0]
			},
			"bones": [
				{
					"name": "root",
					"pivot": [0, 24, 0]
				},
				{
					"name": "Body",
					"parent": "root",
					"pivot": [0, 12.5, -5],
					"cubes": [
						{"origin": [-9, 5.5, -5], "size": [18, 12, 14], "uv": [87, 2]}
					]
				},
				{
					"name": "BodyUpper",
					"parent": "Body",
					"pivot": [0, 12.9, -4.4],
					"rotation": [5.22, 0, 0],
					"cubes": [
						{"origin": [-8, 6.1, -12.5], "size": [16, 11, 10], "uv": [34, 15]}
					]
				},
				{
					"name": "Neck",
					"parent": "BodyUpper",
					"pivot": [0, 14, -11.9],
					"rotation": [-5.22, 0, 0],
					"cubes": [
						{"origin": [-4, 9, -20.4], "size": [8, 7, 9], "uv": [57, 48]}
					]
				},
				{
					"name": "Head",
					"parent": "Neck",
					"pivot": [0, 14.3, -17.9],
					"rotation": [5.22, 1.00023, 0],
					"cubes": [
						{"origin": [-3.43324, 29.22389, -23.89028], "size": [7, 4, 6], "pivot": [0.06676, 17.52389, 3.50972], "rotation": [39.13, 0, 1.0002], "uv": [0, 18]},
						{"origin": [-3, 9.2, -25.2], "size": [6, 2, 4], "uv": [21, 17]},
						{"origin": [-17.54591, 19.57077, -20.07144], "size": [4, 2, 6], "pivot": [-12.14591, 5.67077, 1.42856], "rotation": [7.83, -20.87, 21.8702], "uv": [34, 0], "mirror": true},
						{"origin": [-9.42317, 10.94338, -18.3065], "size": [2, 4, 4], "pivot": [-4.82317, 2.54338, 1.6935], "rotation": [7.83, -5.22, 18.26], "uv": [55, 0], "mirror": true},
						{"origin": [13.38339, 19.41078, -20.07144], "size": [4, 2, 6], "pivot": [11.98339, 5.51078, 1.42856], "rotation": [7.83, 20.87, -20.87], "uv": [34, 0]},
						{"origin": [7.42317, 10.94338, -18.3065], "size": [2, 4, 4], "pivot": [4.82317, 2.54338, 1.6935], "rotation": [7.83, 5.22, -18.26], "uv": [55, 0]},
						{"origin": [-4.5, 9.2, -22.9], "size": [9, 7, 7], "uv": [1, 1]}
					]
				},
				{
					"name": "FrontThighL",
					"parent": "BodyUpper",
					"pivot": [-6.5, 10.6, -10.4],
					"rotation": [10.43, 0, 0],
					"cubes": [
						{"origin": [-8.5, -2.25458, -14.25564], "size": [4, 6, 4], "pivot": [0, -2.45458, -1.95564], "rotation": [-15, 0, 0], "uv": [31, 48], "mirror": true},
						{"origin": [-9, 5.6, -12.4], "size": [5, 5, 4], "uv": [31, 37], "mirror": true}
					]
				},
				{
					"name": "FrontThighR",
					"parent": "BodyUpper",
					"pivot": [6.4, 10.6, -10.4],
					"rotation": [10.43, 0, 0],
					"cubes": [
						{"origin": [4.4, -2.25458, -14.25564], "size": [4, 6, 4], "pivot": [0, -2.45458, -1.95564], "rotation": [-15, 0, 0], "uv": [31, 48]},
						{"origin": [3.9, 5.6, -12.4], "size": [5, 5, 4], "uv": [31, 37]}
					]
				},
				{
					"name": "Tail1",
					"parent": "Body",
					"pivot": [0, 13.9, 8],
					"rotation": [-13.04, 0, 0],
					"cubes": [
						{"origin": [-7, 7.9, 6], "size": [14, 9, 9], "uv": [104, 30]}
					]
				},
				{
					"name": "Tail2",
					"parent": "Tail1",
					"pivot": [0, 13.3, 14.7],
					"rotation": [2.61, 0, 0],
					"cubes": [
						{"origin": [-4, 9.8, 13.7], "size": [8, 6, 11], "uv": [139, 39]}
					]
				},
				{
					"name": "Tail3",
					"parent": "Tail2",
					"pivot": [-0.1, 13.2, 23.8],
					"rotation": [7.83, 0, 0],
					"cubes": [
						{"origin": [-4.6, 11.3, 38.4], "size": [9, 4, 6], "uv": [72, 37]},
						{"origin": [-3.1, 11.3, 38.4], "size": [6, 4, 5], "uv": [93, 55]},
						{"origin": [-2.1, 11.8, 23.8], "size": [4, 3, 16], "uv": [162, 41]}
					]
				},
				{
					"name": "BackThighL",
					"parent": "Body",
					"pivot": [-7.5, 13.2, 5.1],
					"rotation": [-5.22, 0, 0],
					"cubes": [
						{"origin": [-10, 5.2, 2.1], "size": [5, 9, 6], "uv": [0, 29], "mirror": true}
					]
				},
				{
					"name": "BackLegL",
					"parent": "BackThighL",
					"pivot": [-7.5, 6.8, 6.8],
					"rotation": [5.22, 0, 0],
					"cubes": [
						{"origin": [-10, 0, 4.3], "size": [5, 2, 4], "uv": [0, 57], "mirror": true},
						{"origin": [-9.5, 0, 4.8], "size": [4, 7, 4], "uv": [0, 44], "mirror": true}
					]
				},
				{
					"name": "BackThighR",
					"parent": "Body",
					"pivot": [7.5, 13.2, 5.1],
					"rotation": [-5.22, 0, 0],
					"cubes": [
						{"origin": [5, 5.2, 2.1], "size": [5, 9, 6], "uv": [0, 29]}
					]
				},
				{
					"name": "BackLegR",
					"parent": "BackThighR",
					"pivot": [7.5, 6.8, 6.8],
					"rotation": [5.22, 0, 0],
					"cubes": [
						{"origin": [5, 0, 4.3], "size": [5, 2, 4], "uv": [0, 57]},
						{"origin": [5.5, 0, 4.8], "size": [4, 7, 4], "uv": [0, 44]}
					]
				}
			]
		}
	]
}